boicl/__init__.py
boicl/aqfxns.py
boicl/asktell.py
boicl/asktellFinetuning.py
boicl/asktellGPR.py
boicl/asktellNearestNeighbor.py
boicl/asktellRidgeRegression.py
boicl/llm_model.py
boicl/pool.py
boicl/tool.py
boicl/version.py
boicl-0.2.0.dist-info/METADATA
boicl-0.2.0.dist-info/WHEEL
boicl-0.2.0.dist-info/top_level.txt
boicl-0.2.0.dist-info/RECORD
