Metadata-Version: 2.4
Name: boicl
Version: 0.2.0
Summary: BayesOPT with In-Context Learning
Home-page: https://github.com/ur-whitelab/BO-ICL
Author: Andrew White
Author-email: andrew.white@rochester.edu
License: MIT
Classifier: Programming Language :: Python :: 3
Classifier: License :: OSI Approved :: MIT License
Classifier: Operating System :: OS Independent
Requires-Dist: numpy
Requires-Dist: langchain
Requires-Dist: langchain_community
Requires-Dist: langchain_openai
Requires-Dist: langchain_anthropic
Requires-Dist: openai
Requires-Dist: faiss-cpu
Requires-Dist: scipy
Requires-Dist: pandas
Requires-Dist: tiktoken
Provides-Extra: gpr
Requires-Dist: scikit-learn; extra == "gpr"
Requires-Dist: torch; extra == "gpr"
Requires-Dist: botorch; extra == "gpr"
Requires-Dist: gpytorch; extra == "gpr"
Dynamic: author
Dynamic: author-email
Dynamic: classifier
Dynamic: description
Dynamic: description-content-type
Dynamic: home-page
Dynamic: license
Dynamic: provides-extra
Dynamic: requires-dist
Dynamic: summary
